mcneelat/__init__.py
mcneelat/pyutils/__init__.py
mcneelat/pyutils/anomali.py
mcneelat/pyutils/confutils.py
mcneelat/pyutils/crowdstrike.py
mcneelat/pyutils/dbutils.py
mcneelat/pyutils/digitalshadows.py
mcneelat/pyutils/directoryutils.py
mcneelat/pyutils/dnsutils.py
mcneelat/pyutils/fileutils.py
mcneelat/pyutils/kafkautils.py
mcneelat/pyutils/netutils.py
mcneelat_pyutils-1.9.0.dist-info/LICENSE
mcneelat_pyutils-1.9.0.dist-info/METADATA
mcneelat_pyutils-1.9.0.dist-info/WHEEL
mcneelat_pyutils-1.9.0.dist-info/top_level.txt
mcneelat_pyutils-1.9.0.dist-info/RECORD
