Metadata-Version: 2.1
Name: mcneelat-pyutils
Version: 1.9.0
Summary: A collection of helpful Python utilities to simplify dealing with databases, Kafka, and more.
Home-page: https://github.com/tommym89/pyutils
Author: Tommy McNeela
Author-email: mcneelat@gmail.com
License: GPLv3
Platform: UNKNOWN
Classifier: Programming Language :: Python :: 2
Classifier: Programming Language :: Python :: 2.7
Classifier: Programming Language :: Python :: 3
Classifier: Programming Language :: Python :: 3.7
Requires-Dist: dnspython
Requires-Dist: kafka-python
Requires-Dist: psycopg2-binary
Requires-Dist: python-ldap
Requires-Dist: requests
